build/lib/build/lib/build/lib/build/lib/lie/__init__.py
build/lib/build/lib/build/lib/lie/__init__.py
build/lib/build/lib/build/lib/lie-ai/__init__.py
build/lib/build/lib/lie/__init__.py
build/lib/build/lib/lie-ai/__init__.py
build/lib/build/lib/lie_ai/__init__.py
build/lib/lie/__init__.py
build/lib/lie-ai/__init__.py
build/lib/lie_ai/__init__.py
lie/__init__.py
lie-ai/__init__.py
lie_ai/__init__.py
lie_ai-0.1.2.dist-info/METADATA
lie_ai-0.1.2.dist-info/WHEEL
lie_ai-0.1.2.dist-info/entry_points.txt
lie_ai-0.1.2.dist-info/top_level.txt
lie_ai-0.1.2.dist-info/RECORD
