Metadata-Version: 2.4
Name: lie_ai
Version: 0.1.2
Summary: A CLI tool for asking LLM questions like 'which is bigger, 9.11 or 9.4?'
License: MIT
Requires-Python: >=3.8
Requires-Dist: openai
